<?xml version='1.0' encoding='utf-8'?>
<annotation><filename>domain1/000090.jpg</filename>
  <segmented>0</segmented>
  <size><width>1140</width>
    <height>539</height>
    <depth>3</depth>
  </size>
  <object><name>battery</name>
    <pose>Unspecified</pose>
    <truncated>0</truncated>
    <difficult>0</difficult>
    <check>0</check>
    <bndbox><xmin>200</xmin>
      <ymin>413</ymin>
      <xmax>269</xmax>
      <ymax>440</ymax>
    </bndbox>
  </object>
  <object><name>scissors</name>
    <pose>Unspecified</pose>
    <truncated>0</truncated>
    <difficult>0</difficult>
    <check>0</check>
    <bndbox><xmin>133</xmin>
      <ymin>198</ymin>
      <xmax>421</xmax>
      <ymax>312</ymax>
    </bndbox>
  </object>
</annotation>