<?xml version='1.0' encoding='utf-8'?>
<annotation><filename>domain1/000269.jpg</filename>
  <segmented>0</segmented>
  <size><width>688</width>
    <height>673</height>
    <depth>3</depth>
  </size>
  <object><name>battery</name>
    <pose>Unspecified</pose>
    <truncated>0</truncated>
    <difficult>0</difficult>
    <check>0</check>
    <bndbox><xmin>58</xmin>
      <ymin>364</ymin>
      <xmax>88</xmax>
      <ymax>414</ymax>
    </bndbox>
  </object>
  <object><name>battery</name>
    <pose>Unspecified</pose>
    <truncated>0</truncated>
    <difficult>0</difficult>
    <check>0</check>
    <bndbox><xmin>77</xmin>
      <ymin>366</ymin>
      <xmax>102</xmax>
      <ymax>414</ymax>
    </bndbox>
  </object>
  <object><name>battery</name>
    <pose>Unspecified</pose>
    <truncated>0</truncated>
    <difficult>0</difficult>
    <check>0</check>
    <bndbox><xmin>58</xmin>
      <ymin>467</ymin>
      <xmax>99</xmax>
      <ymax>526</ymax>
    </bndbox>
  </object>
  </annotation>