<?xml version='1.0' encoding='utf-8'?>
<annotation>
	<filename>domain1/001217.jpg</filename>
	<segmented>0</segmented>
	<size>
		<width>974</width>
		<height>629</height>
		<depth>3</depth>
	</size>
	<object>
		<name>knife</name>
		<pose>Unspecified</pose>
		<truncated>0</truncated>
		<difficult>0</difficult>
		<check>0</check>
		<bndbox>
			<xmin>642</xmin>
			<ymin>177</ymin>
			<xmax>674</xmax>
			<ymax>279</ymax>
		</bndbox>
	</object>
	<object>
		<name>battery</name>
		<pose>Unspecified</pose>
		<truncated>0</truncated>
		<difficult>0</difficult>
		<check>0</check>
		<bndbox>
			<xmin>559</xmin>
			<ymin>198</ymin>
			<xmax>592</xmax>
			<ymax>305</ymax>
		</bndbox>
	</object>
	<object>
		<name>knife</name>
		<pose>Unspecified</pose>
		<truncated>0</truncated>
		<difficult>0</difficult>
		<check>0</check>
		<bndbox>
			<xmin>143</xmin>
			<ymin>205</ymin>
			<xmax>180</xmax>
			<ymax>445</ymax>
		</bndbox>
	</object>
	<object>
		<name>knife</name>
		<pose>Unspecified</pose>
		<truncated>0</truncated>
		<difficult>0</difficult>
		<check>0</check>
		<bndbox>
			<xmin>525</xmin>
			<ymin>364</ymin>
			<xmax>615</xmax>
			<ymax>384</ymax>
		</bndbox>
	</object>
	</annotation>